ntripbrowser/__init__.py
ntripbrowser/browser.py
ntripbrowser/constants.py
ntripbrowser/exceptions.py
ntripbrowser/ntripbrowser.py
ntripbrowser-2.2.3.dist-info/LICENSE
ntripbrowser-2.2.3.dist-info/METADATA
ntripbrowser-2.2.3.dist-info/WHEEL
ntripbrowser-2.2.3.dist-info/entry_points.txt
ntripbrowser-2.2.3.dist-info/top_level.txt
ntripbrowser-2.2.3.dist-info/RECORD
